vypr/__init__.py
vypr/errors.py
vypr/engine/__init__.py
vypr/engine/graph.py
vypr/engine/node.py
vypr/engine/validator.py
vypr/engine/value.py
vypr-0.0.0.dist-info/LICENSE
vypr-0.0.0.dist-info/METADATA
vypr-0.0.0.dist-info/WHEEL
vypr-0.0.0.dist-info/top_level.txt
vypr-0.0.0.dist-info/RECORD
